LICENSE
README.md
setup.py
tap_dynamodb/__init__.py
tap_dynamodb/deserialize.py
tap_dynamodb/discover.py
tap_dynamodb/dynamodb.py
tap_dynamodb/sync.py
tap_dynamodb.egg-info/PKG-INFO
tap_dynamodb.egg-info/SOURCES.txt
tap_dynamodb.egg-info/dependency_links.txt
tap_dynamodb.egg-info/entry_points.txt
tap_dynamodb.egg-info/requires.txt
tap_dynamodb.egg-info/top_level.txt
tap_dynamodb/sync_strategies/__init__.py
tap_dynamodb/sync_strategies/full_table.py
tap_dynamodb/sync_strategies/log_based.py
tests/test_dynamodb_discovery.py
tests/test_dynamodb_full_table_interruptible_sync.py
tests/test_dynamodb_full_table_primary_and_hash_key_projections.py
tests/test_dynamodb_full_table_sync.py
tests/test_dynamodb_log_based.py
tests/test_dynamodb_log_based_interruptible.py
tests/test_dynamodb_log_based_parent_child_data.py
tests/test_dynamodb_log_based_primary_and_hash_key_projections.py
tests/test_dynamodb_log_based_projections.py
tests/test_dynamodb_projections.py